{
  "Version": "3.4.0+dev", 
  "Began": "Fri May  5 21:18:58 2023", 
  "Command line": "ior -a MPIIO -w -b 100M -t 2M -O summaryFormat=JSON --mpiio.hintsFileName=hintsF_bo -i 10", 
  "Machine": "Linux cn140", 
  "tests": [
    {
    "TestID": 0, 
    "StartTime": "Fri May  5 21:18:58 2023"    , "Path": "testFile","Capacity": "9881.5 TiB", "Used Capacity": "18.0%","Inodes": "8192.0 Mi", "Used Inodes" : "9.5%"
, 
    "Parameters": {
      "testID": 0, 
      "refnum": 0, 
      "api": "MPIIO", 
      "platform": "cn(Linux)", 
      "testFileName": "testFile", 
      "deadlineForStonewall": 0, 
      "stoneWallingWearOut": 0, 
      "maxTimeDuration": 0, 
      "outlierThreshold": 0, 
      "options": "(null)", 
      "dryRun": 0, 
      "nodes": 64, 
      "memoryPerTask": 0, 
      "memoryPerNode": 0, 
      "tasksPerNode": 1, 
      "repetitions": 10, 
      "multiFile": 0, 
      "interTestDelay": 0, 
      "fsync": 0, 
      "fsyncperwrite": 0, 
      "useExistingTestFile": 0, 
      "uniqueDir": 0, 
      "singleXferAttempt": 0, 
      "readFile": 0, 
      "writeFile": 1, 
      "filePerProc": 0, 
      "reorderTasks": 0, 
      "reorderTasksRandom": 0, 
      "reorderTasksRandomSeed": 0, 
      "randomOffset": 0, 
      "checkWrite": 0, 
      "checkRead": 0, 
      "dataPacketType": 0, 
      "keepFile": 0, 
      "keepFileWithError": 0, 
      "warningAsErrors": 0, 
      "verbose": 0, 
      "data packet type": "g", 
      "setTimeStampSignature/incompressibleSeed": 0, 
      "collective": 0, 
      "segmentCount": 1, 
      "transferSize": 2097152, 
      "blockSize": 104857600
    }
, 
    "Options": {
      "api": "MPIIO", 
      "apiVersion": "(3.1)", 
      "test filename": "testFile", 
      "access": "single-shared-file", 
      "type": "independent", 
      "segments": 1, 
      "ordering in a file": "sequential", 
      "ordering inter file": "no tasks offsets", 
      "nodes": 64, 
      "tasks": 64, 
      "clients per node": 1, 
      "repetitions": 10, 
      "xfersize": "2 MiB", 
      "blocksize": "100 MiB", 
      "aggregate filesize": "6.25 GiB"
    }
, 
    "Results": [
            {
        "access": "write", 
        "bwMiB": 5614.2518, 
        "blockKiB": 102400.0000, 
        "xferKiB": 2048.0000, 
        "iops": 3191.4308, 
        "latency": 0.0082, 
        "openTime": 0.1234, 
        "wrRdTime": 1.0027, 
        "closeTime": 0.7691, 
        "totalTime": 1.1400
      }
, 
            {
        "access": "write", 
        "bwMiB": 3175.8884, 
        "blockKiB": 102400.0000, 
        "xferKiB": 2048.0000, 
        "iops": 1748.7545, 
        "latency": 0.0068, 
        "openTime": 0.1842, 
        "wrRdTime": 1.8299, 
        "closeTime": 1.6156, 
        "totalTime": 2.0152
      }
, 
            {
        "access": "write", 
        "bwMiB": 1887.3778, 
        "blockKiB": 102400.0000, 
        "xferKiB": 2048.0000, 
        "iops": 1084.2260, 
        "latency": 0.0084, 
        "openTime": 0.4370, 
        "wrRdTime": 2.9514, 
        "closeTime": 2.7044, 
        "totalTime": 3.3909
      }
, 
            {
        "access": "write", 
        "bwMiB": 2633.2495, 
        "blockKiB": 102400.0000, 
        "xferKiB": 2048.0000, 
        "iops": 1611.8008, 
        "latency": 0.0157, 
        "openTime": 0.4429, 
        "wrRdTime": 1.9854, 
        "closeTime": 1.7495, 
        "totalTime": 2.4305
      }
, 
            {
        "access": "write", 
        "bwMiB": 5986.3041, 
        "blockKiB": 102400.0000, 
        "xferKiB": 2048.0000, 
        "iops": 3138.1345, 
        "latency": 0.0178, 
        "openTime": 0.0384, 
        "wrRdTime": 1.0197, 
        "closeTime": 0.7964, 
        "totalTime": 1.0691
      }
, 
            {
        "access": "write", 
        "bwMiB": 5341.3900, 
        "blockKiB": 102400.0000, 
        "xferKiB": 2048.0000, 
        "iops": 3049.2684, 
        "latency": 0.0074, 
        "openTime": 0.1086, 
        "wrRdTime": 1.0494, 
        "closeTime": 0.8214, 
        "totalTime": 1.1982
      }
, 
            {
        "access": "write", 
        "bwMiB": 2709.1919, 
        "blockKiB": 102400.0000, 
        "xferKiB": 2048.0000, 
        "iops": 1606.2878, 
        "latency": 0.0094, 
        "openTime": 0.3686, 
        "wrRdTime": 1.9922, 
        "closeTime": 1.7647, 
        "totalTime": 2.3623
      }
, 
            {
        "access": "write", 
        "bwMiB": 5355.4736, 
        "blockKiB": 102400.0000, 
        "xferKiB": 2048.0000, 
        "iops": 3364.3056, 
        "latency": 0.0073, 
        "openTime": 0.2307, 
        "wrRdTime": 0.9512, 
        "closeTime": 0.6766, 
        "totalTime": 1.1950
      }
, 
            {
        "access": "write", 
        "bwMiB": 2743.3831, 
        "blockKiB": 102400.0000, 
        "xferKiB": 2048.0000, 
        "iops": 1511.4308, 
        "latency": 0.0127, 
        "openTime": 0.2148, 
        "wrRdTime": 2.1172, 
        "closeTime": 1.9529, 
        "totalTime": 2.3329
      }
, 
            {
        "access": "write", 
        "bwMiB": 675.8907, 
        "blockKiB": 102400.0000, 
        "xferKiB": 2048.0000, 
        "iops": 1132.2423, 
        "latency": 0.0122, 
        "openTime": 6.6423, 
        "wrRdTime": 2.8263, 
        "closeTime": 2.5282, 
        "totalTime": 9.4690
      }
]

  }
]
, 
"summary": [
    {
    "operation": "write", 
    "API": "MPIIO", 
    "TestID": 0, 
    "ReferenceNumber": 0, 
    "segmentCount": 1, 
    "blockSize": 104857600, 
    "transferSize": 2097152, 
    "numTasks": 64, 
    "tasksPerNode": 1, 
    "repetitions": 10, 
    "filePerProc": 0, 
    "reorderTasks": 0, 
    "taskPerNodeOffset": 1, 
    "reorderTasksRandom": 0, 
    "reorderTasksRandomSeed": 0, 
    "bwMaxMIB": 5986.3041, 
    "bwMinMIB": 675.8907, 
    "bwMeanMIB": 3612.2401, 
    "bwStdMIB": 1731.7501, 
    "OPsMax": 2993.1521, 
    "OPsMin": 337.9454, 
    "OPsMean": 1806.1201, 
    "OPsSD": 865.8751, 
    "MeanTime": 2.6603, 
    "xsizeMiB": 6400.0000
  }
]
, 
"Finished": "Fri May  5 21:19:27 2023"
}
